MANIFEST.in
README.rst
setup.cfg
setup.py
versioneer.py
codetransformer/__init__.py
codetransformer/_version.py
codetransformer/code.py
codetransformer/core.py
codetransformer/instructions.py
codetransformer/patterns.py
codetransformer/pycharm.py
codetransformer/decompiler/_343.py
codetransformer/decompiler/__init__.py
codetransformer/tests/__init__.py
codetransformer/tests/test_code.py
codetransformer/tests/test_core.py
codetransformer/tests/test_decompiler.py
codetransformer/tests/test_instructions.py
codetransformer/transformers/__init__.py
codetransformer/transformers/add2mul.py
codetransformer/transformers/constants.py
codetransformer/transformers/interpolated_strings.py
codetransformer/transformers/literals.py
codetransformer/transformers/pattern_matched_exceptions.py
codetransformer/transformers/precomputed_slices.py
codetransformer/transformers/tests/__init__.py
codetransformer/transformers/tests/test_add2mul.py
codetransformer/transformers/tests/test_constants.py
codetransformer/transformers/tests/test_exc_patterns.py
codetransformer/transformers/tests/test_interpolated_strings.py
codetransformer/transformers/tests/test_literals.py
codetransformer/transformers/tests/test_precomputed_slices.py
codetransformer/utils/__init__.py
codetransformer/utils/disBackport.py
codetransformer/utils/functional.py
codetransformer/utils/immutable.py
codetransformer/utils/instance.py
codetransformer/utils/newChainMap.py
codetransformer/utils/no_default.py
codetransformer/utils/pretty.py
codetransformer/utils/stackeffect.py
codetransformer/utils/to_bytes.py
codetransformer/utils/tests/__init__.py
codetransformer/utils/tests/test_immutable.py
codetransformer/utils/tests/test_pretty.py
codetransformer_py2.egg-info/PKG-INFO
codetransformer_py2.egg-info/SOURCES.txt
codetransformer_py2.egg-info/dependency_links.txt
codetransformer_py2.egg-info/requires.txt
codetransformer_py2.egg-info/top_level.txt