Metadata-Version: 1.1
Name: codetransformer-py2
Version: 0.7.3
Summary: Python code object transformers
Home-page: https://github.com/brthor/codetransformer-py2
Author: Joe Jevnik, Scott Sanderson, and Bryan Thornbury
Author-email: joejev@gmail.com
License: GPL-2
Platform: UNKNOWN
Classifier: Development Status :: 3 - Alpha
Classifier: License :: OSI Approved :: GNU General Public License v2 (GPLv2)
Classifier: Natural Language :: English
Classifier: Programming Language :: Python :: 2.7
Classifier: Programming Language :: Python :: Implementation :: CPython
Classifier: Operating System :: POSIX
Classifier: Topic :: Software Development :: Pre-processors
